CHANGES.txt
MANIFEST.in
README.txt
bootstrap.py
buildout.cfg
demomapping.cfg
setup.py
babel_obviel.egg-info/PKG-INFO
babel_obviel.egg-info/SOURCES.txt
babel_obviel.egg-info/dependency_links.txt
babel_obviel.egg-info/entry_points.txt
babel_obviel.egg-info/not-zip-safe
babel_obviel.egg-info/requires.txt
babel_obviel.egg-info/top_level.txt
babelobviel/__init__.py
babelobviel/obvt.py
babelobviel/test/__init__.py
babelobviel/test/test_extractor.py
babelobviel/test/test_tokenize.py
babelobviel/test/testdata/test1.html
babelobviel/test/testdata/test1.obvt
babelobviel/test/testdata/test10.obvt
babelobviel/test/testdata/test11.obvt
babelobviel/test/testdata/test12.obvt
babelobviel/test/testdata/test13.obvt
babelobviel/test/testdata/test14.obvt
babelobviel/test/testdata/test15.obvt
babelobviel/test/testdata/test16.obvt
babelobviel/test/testdata/test17.obvt
babelobviel/test/testdata/test18.obvt
babelobviel/test/testdata/test19.obvt
babelobviel/test/testdata/test2.html
babelobviel/test/testdata/test2.obvt
babelobviel/test/testdata/test20.obvt
babelobviel/test/testdata/test21.obvt
babelobviel/test/testdata/test22.obvt
babelobviel/test/testdata/test23.obvt
babelobviel/test/testdata/test24.obvt
babelobviel/test/testdata/test3.obvt
babelobviel/test/testdata/test4.obvt
babelobviel/test/testdata/test5.obvt
babelobviel/test/testdata/test6.obvt
babelobviel/test/testdata/test7.obvt
babelobviel/test/testdata/test8.obvt
babelobviel/test/testdata/test9.obvt