Metadata-Version: 1.0
Name: babel-obviel
Version: 0.7.1
Summary: Obviel Template message extractor for Babel
Home-page: UNKNOWN
Author: Obviel Developers
Author-email: obviel@googlegroups.com
License: BSD
Platform: UNKNOWN
